<odoo>
    <data>
        <!--
            =========================================================
            The following views have been created using odoo scaffold
            They do nothing sensible yet
            =========================================================
          -->

        <template id="listing">
          <ul>
            <li t-foreach="objects" t-as="object">
              <a t-attf-href="#{ root }/objects/#{ object.id }">
                <t t-esc="object.display_name"/>
              </a>
            </li>
          </ul>
        </template>
        <template id="object">
          <h1><t t-esc="object.display_name"/></h1>
          <dl>
            <t t-foreach="object._fields" t-as="field">
              <dt><t t-esc="field"/></dt>
              <dd><t t-esc="object[field]"/></dd>
            </t>
          </dl>
        </template>
        <!--
            =========================================================
            The following template has been copied from google_calendar
            However is seems not to work
            =========================================================
        -->
        <template id="assets_backend_gc" name="calendar_google assets" inherit_id="web.assets_backend">
            <xpath expr="." position="inside">
                <link rel="stylesheet" type="text/scss" href="/calendar_google_handler/static/src/scss/calendar_google_handler.scss"/>
                <script type="text/javascript" src="/calendar_google_handler/static/src/js/calendar_google_handler.js"></script>
            </xpath>
        </template>
    </data>
</odoo>
